{
  "id": "api/core/IterableDifferFactory",
  "title": "\n      IterableDifferFactory\n    ",
  "contents": "\n\n<article>\n  <div class=\"breadcrumb\">\n    <script type=\"application/ld+json\">\n      {\n        \"@context\": \"http://schema.org\",\n        \"@type\": \"BreadcrumbList\",\n        \"itemListElement\": [\n          \n            {\n            \"@type\": \"ListItem\",\n            \"position\": 1,\n            \"item\": {\n              \"@id\": \"https://angular.io//api\",\n              \"name\": \"API\"\n            }\n          }\n            ,{\n            \"@type\": \"ListItem\",\n            \"position\": 2,\n            \"item\": {\n              \"@id\": \"https://angular.io/api/core\",\n              \"name\": \"@angular/core\"\n            }\n          }\n            ,{\n            \"@type\": \"ListItem\",\n            \"position\": 3,\n            \"item\": {\n              \"@id\": \"https://angular.io/api/core/IterableDifferFactory\",\n              \"name\": \"IterableDifferFactory\"\n            }\n          }\n        ]\n      }\n      </script>\n    \n      \n      <a href=\"/api\">API</a>\n    \n      /\n      <a href=\"api/core\">@angular/core</a>\n    \n  </div>\n  <header class=\"api-header\">\n    \n    \n    <label class=\"api-status-label stable\">stable</label>\n    <label class=\"api-type-label interface\">interface</label>\n    <h1 id=\"iterabledifferfactory\"><a title=\"Link to this heading\" class=\"header-link\" aria-hidden=\"true\" href=\"api/core/IterableDifferFactory#iterabledifferfactory\"><i class=\"material-icons\">link</i></a>\n      IterableDifferFactory\n    </h1>\n    <span class=\"version\"></span>\n  </header>\n  <div class=\"page-actions\">\n      <a href=\"api/core/IterableDifferFactory#\"><label class=\"raised page-label\"><i class=\"material-icons\">mode_edit</i>suggest edits</label></a>\n      <a href=\"https://github.com/angular/angular/tree/6.0.0-beta.5/packages/core/src/change_detection/differs/iterable_differs.ts#L122-L131\"><label class=\"raised page-label\"><i class=\"material-icons\">code</i>view source</label></a>\n  </div>\n\n  <div class=\"api-body\">\n    \n  \n  \n  \n  <section class=\"interface-overview\">\n<h2 id=\"interface-overview\"><a title=\"Link to this heading\" class=\"header-link\" aria-hidden=\"true\" href=\"api/core/IterableDifferFactory#interface-overview\"><i class=\"material-icons\">link</i></a>Interface Overview</h2>\n<code-example language=\"ts\" hidecopy=\"true\">\ninterface <a href=\"api/core/IterableDifferFactory\" class=\"code-anchor\">IterableDifferFactory</a> {\n  <a class=\"code-anchor\" href=\"api/core/IterableDifferFactory#supports\">supports(objects: any): boolean</a>\n  <a class=\"code-anchor\" href=\"api/core/IterableDifferFactory#create\">create&#x3C;V>(trackByFn?: TrackByFunction&#x3C;V>): IterableDiffer&#x3C;V></a>\n}\n</code-example>\n\n  \n  \n\n\n  \n  \n\n\n\n</section>\n  \n\n  \n  \n<section class=\"description\">\n  <h2 id=\"description\"><a title=\"Link to this heading\" class=\"header-link\" aria-hidden=\"true\" href=\"api/core/IterableDifferFactory#description\"><i class=\"material-icons\">link</i></a>Description</h2>\n  <p translation-origin=\"off\">Provides a factory for <a href=\"api/core/IterableDiffer\"><code>IterableDiffer</code></a>.</p>\n\n</section>\n\n  \n\n  \n\n<section class=\"instance-methods\">\n  <h2 id=\"methods\"><a title=\"Link to this heading\" class=\"header-link\" aria-hidden=\"true\" href=\"api/core/IterableDifferFactory#methods\"><i class=\"material-icons\">link</i></a>Methods</h2>\n  \n    <a id=\"supports\"></a>\n<table class=\"is-full-width method-table instance-method\">\n  <thead><tr><th><h3 id=\"supports\"><a title=\"Link to this heading\" class=\"header-link\" aria-hidden=\"true\" href=\"api/core/IterableDifferFactory#supports\"><i class=\"material-icons\">link</i></a>\n    supports()\n    \n  </h3></th></tr></thead>\n  <tbody>\n    \n  \n    <tr>\n      <td>\n        \n\n  <code-example language=\"ts\" hidecopy=\"true\" class=\"no-box api-heading\">supports(objects: any): boolean</code-example>\n\n  <h4 class=\"no-anchor\" id=\"parameters\">Parameters</h4>\n  <table class=\"is-full-width list-table parameters-table instance-method-overload-parameters\">\n  <tbody>\n  \n    <tr class=\"instance-method-overload-parameter\">\n      <td class=\"param-name\"><a id=\"\"></a>objects</td>\n      <td class=\"param-description\">\n              <p translation-origin=\"off\"><code>any</code></p>\n        \n      </td>\n    </tr>\n  </tbody>\n</table>\n\n  \n    <h4 class=\"no-anchor\" id=\"returns\">Returns</h4>\n    <p translation-origin=\"off\"><code>boolean</code></p>\n\n  \n\n  \n      </td>\n    </tr>\n  \n  </tbody>\n</table>\n\n  \n    <a id=\"create\"></a>\n<table class=\"is-full-width method-table instance-method\">\n  <thead><tr><th><h3 id=\"create\"><a title=\"Link to this heading\" class=\"header-link\" aria-hidden=\"true\" href=\"api/core/IterableDifferFactory#create\"><i class=\"material-icons\">link</i></a>\n    create()\n    \n  </h3></th></tr></thead>\n  <tbody>\n    \n  \n    <tr>\n      <td>\n        \n\n  <code-example language=\"ts\" hidecopy=\"true\" class=\"no-box api-heading\">create&#x3C;V>(trackByFn?: <a href=\"api/core/TrackByFunction\" class=\"code-anchor\">TrackByFunction</a>&#x3C;V>): <a href=\"api/core/IterableDiffer\" class=\"code-anchor\">IterableDiffer</a>&#x3C;V></code-example>\n\n  <h4 class=\"no-anchor\" id=\"parameters-1\">Parameters</h4>\n  <table class=\"is-full-width list-table parameters-table instance-method-overload-parameters\">\n  <tbody>\n  \n    <tr class=\"instance-method-overload-parameter\">\n      <td class=\"param-name\"><a id=\"\"></a>trackByFn</td>\n      <td class=\"param-description\">\n              <p translation-origin=\"off\">Optional. Default is <code>undefined</code>.</p>\n        <p translation-origin=\"off\"><code><a href=\"api/core/TrackByFunction\" class=\"code-anchor\">TrackByFunction</a><v></v></code></p>\n        \n      </td>\n    </tr>\n  </tbody>\n</table>\n\n  \n    <h4 class=\"no-anchor\" id=\"returns-1\">Returns</h4>\n    <p translation-origin=\"off\"><code><a href=\"api/core/IterableDiffer\" class=\"code-anchor\">IterableDiffer&#x3C;V></a></code></p>\n\n  \n\n  \n      </td>\n    </tr>\n  \n  </tbody>\n</table>\n\n  \n</section>\n\n\n\n  </div>\n</article>\n\n<!-- links to this doc:\n - api/core\n - api/core/IterableDiffers\n-->\n<!-- links from this doc:\n - /api\n - api/core\n - api/core/IterableDiffer\n - api/core/IterableDifferFactory#\n - api/core/IterableDifferFactory#create\n - api/core/IterableDifferFactory#description\n - api/core/IterableDifferFactory#interface-overview\n - api/core/IterableDifferFactory#iterabledifferfactory\n - api/core/IterableDifferFactory#methods\n - api/core/IterableDifferFactory#supports\n - api/core/TrackByFunction\n - https://github.com/angular/angular/tree/6.0.0-beta.5/packages/core/src/change_detection/differs/iterable_differs.ts#L122-L131\n-->"
}