{
  "id": "api/router/RouterEvent",
  "title": "\n      RouterEvent\n    ",
  "contents": "\n\n<article>\n  <div class=\"breadcrumb\">\n    <script type=\"application/ld+json\">\n      {\n        \"@context\": \"http://schema.org\",\n        \"@type\": \"BreadcrumbList\",\n        \"itemListElement\": [\n          \n            {\n            \"@type\": \"ListItem\",\n            \"position\": 1,\n            \"item\": {\n              \"@id\": \"https://angular.io//api\",\n              \"name\": \"API\"\n            }\n          }\n            ,{\n            \"@type\": \"ListItem\",\n            \"position\": 2,\n            \"item\": {\n              \"@id\": \"https://angular.io/api/router\",\n              \"name\": \"@angular/router\"\n            }\n          }\n            ,{\n            \"@type\": \"ListItem\",\n            \"position\": 3,\n            \"item\": {\n              \"@id\": \"https://angular.io/api/router/RouterEvent\",\n              \"name\": \"RouterEvent\"\n            }\n          }\n        ]\n      }\n      </script>\n    \n      \n      <a href=\"/api\">API</a>\n    \n      /\n      <a href=\"api/router\">@angular/router</a>\n    \n  </div>\n  <header class=\"api-header\">\n    \n    <label class=\"api-status-label experimental\">experimental</label>\n    \n    <label class=\"api-type-label class\">class</label>\n    <h1 id=\"routerevent\"><a title=\"Link to this heading\" class=\"header-link\" aria-hidden=\"true\" href=\"api/router/RouterEvent#routerevent\"><i class=\"material-icons\">link</i></a>\n      RouterEvent\n    </h1>\n    <span class=\"version\"></span>\n  </header>\n  <div class=\"page-actions\">\n      <a href=\"api/router/RouterEvent#\"><label class=\"raised page-label\"><i class=\"material-icons\">mode_edit</i>suggest edits</label></a>\n      <a href=\"https://github.com/angular/angular/tree/6.0.0-beta.5/packages/router/src/events.ts#L22-L47\"><label class=\"raised page-label\"><i class=\"material-icons\">code</i>view source</label></a>\n  </div>\n\n  <div class=\"api-body\">\n    \n  <p></p><p translation-origin=\"off\">Base for events the Router goes through, as opposed to events tied to a specific\nRoute. <code><a href=\"api/router/RouterEvent\" class=\"code-anchor\">RouterEvent</a></code>s will only be fired one time for any given navigation.</p>\n<p translation-origin=\"off\">Example:</p>\n<code-example>\nclass MyService {\n  constructor(public router: <a href=\"api/router/Router\" class=\"code-anchor\">Router</a>, logger: Logger) {\n    router.events.filter(e => e instanceof <a href=\"api/router/RouterEvent\" class=\"code-anchor\">RouterEvent</a>).subscribe(e => {\n      logger.log(e.id, e.url);\n    });\n  }\n}\n</code-example>\n<p></p>\n  \n  \n  \n  <section class=\"class-overview\">\n<h2 id=\"overview\"><a title=\"Link to this heading\" class=\"header-link\" aria-hidden=\"true\" href=\"api/router/RouterEvent#overview\"><i class=\"material-icons\">link</i></a>Overview</h2>\n<code-example language=\"ts\" hidecopy=\"true\">\nclass <a href=\"api/router/RouterEvent\" class=\"code-anchor\">RouterEvent</a> {\n  <a class=\"code-anchor\" href=\"api/router/RouterEvent#constructor()\">constructor(id: number, url: string)</a>\n  <a class=\"code-anchor\" href=\"api/router/RouterEvent#id\">id: number</a>\n  <a class=\"code-anchor\" href=\"api/router/RouterEvent#url\">url: string</a>\n}\n</code-example>\n\n  \n  \n  <div class=\"descendants class\">\n    <h2 id=\"subclasses\"><a title=\"Link to this heading\" class=\"header-link\" aria-hidden=\"true\" href=\"api/router/RouterEvent#subclasses\"><i class=\"material-icons\">link</i></a>Subclasses</h2>\n    \n\n<ul>\n  \n    <li>\n      <code><a href=\"api/router/GuardsCheckEnd\" class=\"code-anchor\">GuardsCheckEnd</a></code>\n      \n\n\n    </li>\n  \n    <li>\n      <code><a href=\"api/router/GuardsCheckStart\" class=\"code-anchor\">GuardsCheckStart</a></code>\n      \n\n\n    </li>\n  \n    <li>\n      <code><a href=\"api/router/NavigationCancel\" class=\"code-anchor\">NavigationCancel</a></code>\n      \n\n\n    </li>\n  \n    <li>\n      <code><a href=\"api/router/NavigationEnd\" class=\"code-anchor\">NavigationEnd</a></code>\n      \n\n\n    </li>\n  \n    <li>\n      <code><a href=\"api/router/NavigationError\" class=\"code-anchor\">NavigationError</a></code>\n      \n\n\n    </li>\n  \n    <li>\n      <code><a href=\"api/router/NavigationStart\" class=\"code-anchor\">NavigationStart</a></code>\n      \n\n\n    </li>\n  \n    <li>\n      <code><a href=\"api/router/ResolveEnd\" class=\"code-anchor\">ResolveEnd</a></code>\n      \n\n\n    </li>\n  \n    <li>\n      <code><a href=\"api/router/ResolveStart\" class=\"code-anchor\">ResolveStart</a></code>\n      \n\n\n    </li>\n  \n    <li>\n      <code><a href=\"api/router/RoutesRecognized\" class=\"code-anchor\">RoutesRecognized</a></code>\n      \n\n\n    </li>\n  \n</ul>\n\n\n  </div>\n  \n\n\n\n</section>\n\n  \n  \n    \n    \n    \n\n    \n\n    \n    <h2 id=\"constructor\"><a title=\"Link to this heading\" class=\"header-link\" aria-hidden=\"true\" href=\"api/router/RouterEvent#constructor\"><i class=\"material-icons\">link</i></a>Constructor</h2>\n    <a id=\"constructor()\"></a>\n<table class=\"is-full-width method-table constructor\">\n  \n  <tbody>\n    \n  \n    <tr>\n      <td>\n        \n\n  <code-example language=\"ts\" hidecopy=\"true\" class=\"no-box api-heading\">constructor(id: number, url: string)</code-example>\n\n  <h4 class=\"no-anchor\" id=\"parameters\">Parameters</h4>\n  <table class=\"is-full-width list-table parameters-table constructor-overload-parameters\">\n  <tbody>\n  \n    <tr class=\"constructor-overload-parameter\">\n      <td class=\"param-name\"><a id=\"\"></a>id</td>\n      <td class=\"param-description\">\n              <p translation-origin=\"off\"><code>number</code></p>\n        \n      </td>\n    </tr>\n    <tr class=\"constructor-overload-parameter\">\n      <td class=\"param-name\"><a id=\"\"></a>url</td>\n      <td class=\"param-description\">\n              <p translation-origin=\"off\"><code>string</code></p>\n        \n      </td>\n    </tr>\n  </tbody>\n</table>\n\n  \n\n  \n      </td>\n    </tr>\n  \n  </tbody>\n</table>\n\n\n    \n<section class=\"instance-properties\">\n  <h2 id=\"properties\"><a title=\"Link to this heading\" class=\"header-link\" aria-hidden=\"true\" href=\"api/router/RouterEvent#properties\"><i class=\"material-icons\">link</i></a>Properties</h2>\n  <table class=\"is-full-width list-table properties-table\">\n    <thead>\n      <tr><th>Property</th><th>Type</th><th>Description</th></tr>\n    </thead>\n    <tbody>\n    \n      <tr class=\"instance-property\">\n        <td><a id=\"id\"></a>id</td>\n        <td><label class=\"property-type-label\"><code>number</code></label></td>\n        <td>\n          \n           <span class=\"from-constructor\">Declared in constructor.</span>\n        </td>\n    </tr>\n    \n      <tr class=\"instance-property\">\n        <td><a id=\"url\"></a>url</td>\n        <td><label class=\"property-type-label\"><code>string</code></label></td>\n        <td>\n          \n           <span class=\"from-constructor\">Declared in constructor.</span>\n        </td>\n    </tr>\n    \n    </tbody>\n  </table>\n</section>\n\n    \n\n\n    \n\n  \n  \n\n\n  </div>\n</article>\n\n<!-- links to this doc:\n - api/router\n - api/router/Event\n - api/router/GuardsCheckEnd\n - api/router/GuardsCheckStart\n - api/router/NavigationCancel\n - api/router/NavigationEnd\n - api/router/NavigationError\n - api/router/NavigationStart\n - api/router/ResolveEnd\n - api/router/ResolveStart\n - api/router/RoutesRecognized\n-->\n<!-- links from this doc:\n - /api\n - api/router\n - api/router/GuardsCheckEnd\n - api/router/GuardsCheckStart\n - api/router/NavigationCancel\n - api/router/NavigationEnd\n - api/router/NavigationError\n - api/router/NavigationStart\n - api/router/ResolveEnd\n - api/router/ResolveStart\n - api/router/Router\n - api/router/RouterEvent#\n - api/router/RouterEvent#constructor\n - api/router/RouterEvent#constructor()\n - api/router/RouterEvent#id\n - api/router/RouterEvent#overview\n - api/router/RouterEvent#properties\n - api/router/RouterEvent#routerevent\n - api/router/RouterEvent#subclasses\n - api/router/RouterEvent#url\n - api/router/RoutesRecognized\n - https://github.com/angular/angular/tree/6.0.0-beta.5/packages/router/src/events.ts#L22-L47\n-->"
}